CHANGELOG.txt
LICENCE.txt
MANIFEST.in
README.txt
setup.py
mediaplanning/__init__.py
mediaplanning.egg-info/PKG-INFO
mediaplanning.egg-info/SOURCES.txt
mediaplanning.egg-info/dependency_links.txt
mediaplanning.egg-info/top_level.txt