Metadata-Version: 1.1
Name: mediaplanning
Version: 0.0.5
Summary: Python package for media planning
Home-page: https://github.com/maazkhan86/mediaplanning
Author: Maaz A. Khan
Author-email: maazkhan700@gmail.com
License: MIT
Keywords: media planning digital online offline
Platform: UNKNOWN
Classifier: Development Status :: 5 - Production/Stable
Classifier: Intended Audience :: Education
Classifier: Operating System :: Microsoft :: Windows :: Windows 10
Classifier: License :: OSI Approved :: MIT License
Classifier: Programming Language :: Python :: 3
